etherhound_core-0.1.2b1.dist-info/licenses/LICENSE.txt
houndcore/__init__.py
houndcore/config.py
houndcore/logger.py
houndcore/api/__init__.py
houndcore/api/app.py
houndcore/api/dependencies.py
houndcore/api/response.py
houndcore/api/routes/__init__.py
houndcore/api/routes/poll.py
houndcore/api/routes/router.py
houndcore/api/routes/subscribe.py
houndcore/api/routes/unsubscribe.py
houndcore/api/schema/__init__.py
houndcore/api/schema/context.py
houndcore/api/schema/subscription.py
houndcore/app/__init__.py
houndcore/app/dispatcher.py
houndcore/app/errors/__init__.py
houndcore/app/errors/incorrect_rpc.py
houndcore/app/scanners/__init__.py
houndcore/app/scanners/base.py
houndcore/app/scanners/subscription_scanner.py
houndcore/app/types/__init__.py
houndcore/app/types/context.py
houndcore/app/types/subscription.py
houndcore/cli/__init__.py
houndcore/cli/__main__.py
houndcore/cli/utils.py
etherhound_core-0.1.2b1.dist-info/METADATA
etherhound_core-0.1.2b1.dist-info/WHEEL
etherhound_core-0.1.2b1.dist-info/entry_points.txt
etherhound_core-0.1.2b1.dist-info/top_level.txt
etherhound_core-0.1.2b1.dist-info/RECORD
