Metadata-Version: 2.4
Name: etherhound-core
Version: 0.1.2b1
Summary: EtherHound Core - Blockchain Event Scanner Server
Author: Spicy Penguin
Requires-Python: >=3.11
License-File: LICENSE.txt
Requires-Dist: fastapi[standard]
Requires-Dist: python-dotenv
Requires-Dist: web3
Requires-Dist: pydantic
Requires-Dist: typer
Dynamic: license-file
Dynamic: requires-python
